<?xml version="1.0" encoding="utf-8"?>

<LanguageData>

	<N_PackedDirt.label>втоптана земля</N_PackedDirt.label>
	<N_PackedDirt.description>Витоптана земля десятками ніг мешканців племені.</N_PackedDirt.description>


	<N_LetherFlor.label>шкіряний килим</N_LetherFlor.label>
	<N_LetherFlor.description>Підлогове покриття зі шкіри. Порадує самолюбство вождя.</N_LetherFlor.description>
	
	<N_LetherFlorPlain.label>шкіряний килим</N_LetherFlorPlain.label>
	<N_LetherFlorPlain.description>Підлогове покриття зі шкіри. Порадує самолюбство вождя.</N_LetherFlorPlain.description>

	<N_LetherFlorDog.label>шкіряний килим з шкіри собаки</N_LetherFlorDog.label>
	<N_LetherFlorDog.description>Підлогове покриття зі шкіри. Порадує самолюбство вождя.</N_LetherFlorDog.description>

	<N_LetherFlorWolf.label>шкіряний килим з вовчої шкіри</N_LetherFlorWolf.label>
	<N_LetherFlorWolf.description>Підлогове покриття зі шкіри. Порадує самолюбство вождя.</N_LetherFlorWolf.description>

	<N_LetherFlorPanthera.label>шкіряний килим зі шкіри пантери</N_LetherFlorPanthera.label>
	<N_LetherFlorPanthera.description>Підлогове покриття зі шкіри. Порадує самолюбство вождя.</N_LetherFlorPanthera.description>

	<N_LetherFlorCamel.label>шкіряний килим зі шкіри верблюда</N_LetherFlorCamel.label>
	<N_LetherFlorCamel.description>Підлогове покриття зі шкіри. Порадує самолюбство вождя.</N_LetherFlorCamel.description>

	<N_LetherFlorBluefur.label>шкіряний килим із блакитного хутра</N_LetherFlorBluefur.label>
	<N_LetherFlorBluefur.description>Підлогове покриття зі шкіри. Порадує самолюбство вождя.</N_LetherFlorBluefur.description>

	<N_LetherFlorBear.label>шкіряний килим зі шкіри ведмедя</N_LetherFlorBear.label>
	<N_LetherFlorBear.description>Підлогове покриття зі шкіри. Порадує самолюбство вождя.</N_LetherFlorBear.description>

	<N_LetherFlorHuman.label>шкіряний килим з людської шкіри</N_LetherFlorHuman.label>
	<N_LetherFlorHuman.description>Підлогове покриття зі шкіри. Порадує самолюбство вождя.</N_LetherFlorHuman.description>

	<N_LetherFlorPig.label>шкіряний килим зі свинячої шкіри</N_LetherFlorPig.label>
	<N_LetherFlorPig.description>Підлогове покриття зі шкіри. Порадує самолюбство вождя.</N_LetherFlorPig.description>

	<N_LetherFlorLight.label>шкіряний килим із легкої шкіри</N_LetherFlorLight.label>
	<N_LetherFlorLight.description>Підлогове покриття зі шкіри. Порадує самолюбство вождя.</N_LetherFlorLight.description>

	<N_LetherFlorBird.label>шкіряний килим із пташиної шкіри</N_LetherFlorBird.label>
	<N_LetherFlorBird.description>Підлогове покриття зі шкіри. Порадує самолюбство вождя.</N_LetherFlorBird.description>

	<N_LetherFlorFox.label>шкіряний килим зі шкіри лисиці</N_LetherFlorFox.label>
	<N_LetherFlorFox.description>Напольное покрытие из кожи. Порадует  самолюбие вождя.</N_LetherFlorFox.description>

	<N_LetherFlorLizard.label>шкіряний килим зі шкіри рептилії</N_LetherFlorLizard.label>
	<N_LetherFlorLizard.description>Підлогове покриття зі шкіри. Порадує самолюбство вождя.</N_LetherFlorLizard.description>

	<N_LetherFlorElephant.label>шкіряний килим зі шкіри слона</N_LetherFlorElephant.label>
	<N_LetherFlorElephant.description>Підлогове покриття зі шкіри. Порадує самолюбство вождя.</N_LetherFlorElephant.description>

	<N_LetherFlorHeavy.label>шкіряний килим із товстої шкіри</N_LetherFlorHeavy.label>
	<N_LetherFlorHeavy.description>Підлогове покриття зі шкіри. Порадує самолюбство вождя.</N_LetherFlorHeavy.description>

	<N_LetherFlorRhinoceros.label>шкіряний килим зі шкіри носорога</N_LetherFlorRhinoceros.label>
	<N_LetherFlorRhinoceros.description>Підлогове покриття зі шкіри. Порадує самолюбство вождя.</N_LetherFlorRhinoceros.description>

	<N_LetherFlorThrumbo.label>шкіряний килим з хутра трумбо</N_LetherFlorThrumbo.label>
	<N_LetherFlorThrumbo.description>Підлогове покриття зі шкіри. Порадує самолюбство вождя.</N_LetherFlorThrumbo.description>
	
</LanguageData>
